terminalos/__init__.py
terminalos/__main__.py
terminalos/cli.py
terminalos/apps/__init__.py
terminalos/apps/calculator.py
terminalos/apps/file_manager.py
terminalos/apps/system_monitor.py
terminalos/apps/text_editor.py
terminalos/core/__init__.py
terminalos/core/app.py
terminalos-1.0.2.dist-info/LICENSE
terminalos-1.0.2.dist-info/METADATA
terminalos-1.0.2.dist-info/WHEEL
terminalos-1.0.2.dist-info/entry_points.txt
terminalos-1.0.2.dist-info/top_level.txt
terminalos-1.0.2.dist-info/RECORD
