Metadata-Version: 2.1
Name: terminalos
Version: 1.0.2
Summary: A complete operating system experience in your terminal
Home-page: https://github.com/000xs/terminalos
Author: 000x
Author-email: 000x <SITHUMSS9122@gmail.com>
License: MIT
Project-URL: Homepage, https://github.com/000xs/terminalos
Project-URL: Documentation, https://terminalos.readthedocs.io/
Project-URL: Repository, https://github.com/000xs/terminalos
Project-URL: Bug Tracker, https://github.com/000xs/terminalos/issues
Keywords: terminal,os,tui,cli,desktop
Classifier: Development Status :: 4 - Beta
Classifier: Intended Audience :: Developers
Classifier: Topic :: Terminals
Classifier: License :: OSI Approved :: MIT License
Classifier: Programming Language :: Python :: 3
Requires-Python: >=3.8
License-File: LICENSE
Requires-Dist: textual>=0.41.0
Requires-Dist: rich>=13.0.0
Requires-Dist: click>=8.1.0
Requires-Dist: psutil>=5.9.0
Requires-Dist: pyfiglet>=0.8.0
Requires-Dist: pygments>=2.14.0
Requires-Dist: watchdog>=3.0.0
Requires-Dist: pyyaml>=6.0
Provides-Extra: audio
Requires-Dist: pygame>=2.3.0; extra == "audio"
Requires-Dist: mutagen>=1.47.0; extra == "audio"
Provides-Extra: dev
Requires-Dist: pytest>=7.0.0; extra == "dev"
Requires-Dist: pytest-cov>=4.0.0; extra == "dev"
Requires-Dist: pytest-asyncio>=0.21.0; extra == "dev"
Requires-Dist: black>=22.0.0; extra == "dev"
Requires-Dist: flake8>=5.0.0; extra == "dev"
Requires-Dist: mypy>=0.991; extra == "dev"
Requires-Dist: pre-commit>=2.20.0; extra == "dev"
Requires-Dist: tox>=4.0.0; extra == "dev"
Requires-Dist: sphinx>=5.0.0; extra == "dev"
Requires-Dist: sphinx-rtd-theme>=1.2.0; extra == "dev"
Provides-Extra: media
Requires-Dist: pillow>=9.0.0; extra == "media"
Requires-Dist: opencv-python>=4.5.0; extra == "media"
